vops/__init__.py
vops/container.py
vops/exceptions.py
vops/graphing.py
vops/scraping.py
vops-0.0.24.dist-info/LICENSE
vops-0.0.24.dist-info/METADATA
vops-0.0.24.dist-info/WHEEL
vops-0.0.24.dist-info/top_level.txt
vops-0.0.24.dist-info/RECORD
